aiomyorm/__init__.py
aiomyorm/connection.py
aiomyorm/field.py
aiomyorm/lib.py
aiomyorm/log.py
aiomyorm/model.py
aiomyorm/set_config.py
aiomyorm/engine/__init__.py
aiomyorm/engine/mysql.py
aiomyorm/engine/sqlite.py
tests/__init__.py
tests/test_mysql/__init__.py
tests/test_mysql/config.py
tests/test_mysql/test_mysql.py
tests/test_sqlite/__init__.py
tests/test_sqlite/test_sqlite.py
aiomyorm-0.2.2.dist-info/LICENSE
aiomyorm-0.2.2.dist-info/METADATA
aiomyorm-0.2.2.dist-info/WHEEL
aiomyorm-0.2.2.dist-info/top_level.txt
aiomyorm-0.2.2.dist-info/RECORD
