Metadata-Version: 2.1
Name: aiomyorm
Version: 0.2.2
Summary: A easy-to-use asynchronous ORM framework
Home-page: https://github.com/yulansp/aiomyorm
Author: yulansp
Author-email: 1301481108@qq.com
License: UNKNOWN
Project-URL: Documentation, https://aiomyorm.readthedocs.io
Project-URL: Source Code, https://github.com/yulansp/aiomyorm
Platform: UNKNOWN
Classifier: Programming Language :: Python :: 3
Classifier: License :: OSI Approved :: MIT License
Classifier: Operating System :: OS Independent
Requires-Python: >=3.6
Requires-Dist: aiomysql (>=0.0.20)
Requires-Dist: aiosqlite (>=0.12.0)
